{"name":"build-javascript","namedChunkGroups":{"polyfill":{"name":"polyfill","assets":[{"name":"webpack-runtime-5b57e3bddeda6792186c.js","size":5522},{"name":"polyfill-f6369386306117b626bd.js","size":85836}],"filteredAssets":0,"assetsSize":91358,"filteredAuxiliaryAssets":2,"auxiliaryAssetsSize":228927},"app":{"name":"app","assets":[{"name":"webpack-runtime-5b57e3bddeda6792186c.js","size":5522},{"name":"styles.d179a8bc542f7838ae04.css","size":41527},{"name":"framework-1647c795356bb48a2249.js","size":128695},{"name":"app-fa3cb1c97b13e4d92e0b.js","size":55044}],"filteredAssets":0,"assetsSize":230788,"filteredAuxiliaryAssets":5,"auxiliaryAssetsSize":619170},"component---src-pages-404-js":{"name":"component---src-pages-404-js","assets":[{"name":"styles.d179a8bc542f7838ae04.css","size":41527},{"name":"commons-768e3a00bb5692f740e5.js","size":50700},{"name":"component---src-pages-404-js-d84276493778ae573981.js","size":611}],"filteredAssets":0,"assetsSize":92838,"filteredAuxiliaryAssets":4,"auxiliaryAssetsSize":273724},"component---src-pages-about-js":{"name":"component---src-pages-about-js","assets":[{"name":"styles.d179a8bc542f7838ae04.css","size":41527},{"name":"commons-768e3a00bb5692f740e5.js","size":50700},{"name":"component---src-pages-about-js-33e57640622065a7f36d.js","size":5424}],"filteredAssets":0,"assetsSize":97651,"filteredAuxiliaryAssets":4,"auxiliaryAssetsSize":280509},"component---src-pages-blog-index-js":{"name":"component---src-pages-blog-index-js","assets":[{"name":"styles.d179a8bc542f7838ae04.css","size":41527},{"name":"commons-768e3a00bb5692f740e5.js","size":50700},{"name":"component---src-pages-blog-index-js-043736fdda985af70ce7.js","size":411}],"filteredAssets":0,"assetsSize":92638,"filteredAuxiliaryAssets":4,"auxiliaryAssetsSize":273516},"component---src-pages-index-js":{"name":"component---src-pages-index-js","assets":[{"name":"styles.d179a8bc542f7838ae04.css","size":41527},{"name":"commons-768e3a00bb5692f740e5.js","size":50700},{"name":"e0023f3c4c230ea0ef8bfb83757e15033c49240e-10f2678c12b92e3732f1.js","size":88323},{"name":"component---src-pages-index-js-aaf59b7d25f7fe624729.js","size":1984}],"filteredAssets":0,"assetsSize":182534,"filteredAuxiliaryAssets":5,"auxiliaryAssetsSize":722087},"component---src-pages-tags-js":{"name":"component---src-pages-tags-js","assets":[{"name":"styles.d179a8bc542f7838ae04.css","size":41527},{"name":"commons-768e3a00bb5692f740e5.js","size":50700},{"name":"component---src-pages-tags-js-2581d9e491e6d6fd274a.js","size":763}],"filteredAssets":0,"assetsSize":92990,"filteredAuxiliaryAssets":4,"auxiliaryAssetsSize":275225},"component---src-templates-blog-template-js":{"name":"component---src-templates-blog-template-js","assets":[{"name":"styles.d179a8bc542f7838ae04.css","size":41527},{"name":"252f366e-1bdfd9917075b6780a6b.js","size":433},{"name":"commons-768e3a00bb5692f740e5.js","size":50700},{"name":"component---src-templates-blog-template-js-7446152e4928aa27ac04.js","size":63591}],"filteredAssets":0,"assetsSize":156251,"filteredAuxiliaryAssets":5,"auxiliaryAssetsSize":2951569},"component---src-templates-post-template-js":{"name":"component---src-templates-post-template-js","assets":[{"name":"styles.d179a8bc542f7838ae04.css","size":41527},{"name":"252f366e-1bdfd9917075b6780a6b.js","size":433},{"name":"commons-768e3a00bb5692f740e5.js","size":50700},{"name":"component---src-templates-post-template-js-ba7853612e61e0bb12d6.js","size":2914}],"filteredAssets":0,"assetsSize":95574,"filteredAuxiliaryAssets":5,"auxiliaryAssetsSize":2710246},"component---src-templates-tag-template-js":{"name":"component---src-templates-tag-template-js","assets":[{"name":"styles.d179a8bc542f7838ae04.css","size":41527},{"name":"252f366e-1bdfd9917075b6780a6b.js","size":433},{"name":"commons-768e3a00bb5692f740e5.js","size":50700},{"name":"e0023f3c4c230ea0ef8bfb83757e15033c49240e-10f2678c12b92e3732f1.js","size":88323},{"name":"component---src-templates-tag-template-js-2da1f9446e8dcb39a7e0.js","size":3194}],"filteredAssets":0,"assetsSize":184177,"filteredAuxiliaryAssets":6,"auxiliaryAssetsSize":3156007}},"assetsByChunkName":{"polyfill":["webpack-runtime-5b57e3bddeda6792186c.js","polyfill-f6369386306117b626bd.js"],"app":["webpack-runtime-5b57e3bddeda6792186c.js","styles.d179a8bc542f7838ae04.css","framework-1647c795356bb48a2249.js","app-fa3cb1c97b13e4d92e0b.js"],"component---src-pages-404-js":["styles.d179a8bc542f7838ae04.css","commons-768e3a00bb5692f740e5.js","component---src-pages-404-js-d84276493778ae573981.js"],"component---src-pages-about-js":["styles.d179a8bc542f7838ae04.css","commons-768e3a00bb5692f740e5.js","component---src-pages-about-js-33e57640622065a7f36d.js"],"component---src-pages-blog-index-js":["styles.d179a8bc542f7838ae04.css","commons-768e3a00bb5692f740e5.js","component---src-pages-blog-index-js-043736fdda985af70ce7.js"],"component---src-pages-index-js":["styles.d179a8bc542f7838ae04.css","commons-768e3a00bb5692f740e5.js","e0023f3c4c230ea0ef8bfb83757e15033c49240e-10f2678c12b92e3732f1.js","component---src-pages-index-js-aaf59b7d25f7fe624729.js"],"component---src-pages-tags-js":["styles.d179a8bc542f7838ae04.css","commons-768e3a00bb5692f740e5.js","component---src-pages-tags-js-2581d9e491e6d6fd274a.js"],"component---src-templates-blog-template-js":["styles.d179a8bc542f7838ae04.css","252f366e-1bdfd9917075b6780a6b.js","commons-768e3a00bb5692f740e5.js","component---src-templates-blog-template-js-7446152e4928aa27ac04.js"],"component---src-templates-post-template-js":["styles.d179a8bc542f7838ae04.css","252f366e-1bdfd9917075b6780a6b.js","commons-768e3a00bb5692f740e5.js","component---src-templates-post-template-js-ba7853612e61e0bb12d6.js"],"component---src-templates-tag-template-js":["styles.d179a8bc542f7838ae04.css","252f366e-1bdfd9917075b6780a6b.js","commons-768e3a00bb5692f740e5.js","e0023f3c4c230ea0ef8bfb83757e15033c49240e-10f2678c12b92e3732f1.js","component---src-templates-tag-template-js-2da1f9446e8dcb39a7e0.js"]},"childAssetsByChunkName":{}}